{
  "posts": [
    {
      "name": "Jane Doe",
      "text": "I had the amazing opprtunity to dance at PNW Ballet this week!",
      "content": "Image",
      "url": "https://www.choozientertainment.com/wp-content/uploads/2016/07/313D0CDD00000578-3448209-image-m-78_1455568033306.jpg",
      "date": "10-03-2020",
      "id": "1"
    },
    {
      "name": "Jane Doe",
      "text": "I had the amazing opprtunity to dance at PNW Ballet this week!",
      "content": "Video",
      "url": "https://www.youtube.com/watch?v=5OzrATk6Y9o",
      "date": "10-03-2020",
      "id": "1"
    },
    {
      "name": "Jane Doe",
      "text": "I had the amazing opprtunity to dance at PNW Ballet this week!",
      "content": "Image",
      "url": "https://www.choozientertainment.com/wp-content/uploads/2016/07/313D0CDD00000578-3448209-image-m-78_1455568033306.jpg",
      "date": "10-03-2020",
      "id": "1"
    },
    {
      "name": "Charlie Brown",
      "text": "I had a great time at the SpaceX Launch!",
      "content": "Video",
      "url": "https://www.youtube.com/watch?v=bnChQbxLkkI",
      "date": "11-16-2020",
      "id": "v-8LBAY"
    }
  ]
}